llama_index/embeddings/fastembed/__init__.py
llama_index/embeddings/fastembed/base.py
llama_index_embeddings_fastembed-0.4.1.dist-info/METADATA
llama_index_embeddings_fastembed-0.4.1.dist-info/WHEEL
llama_index_embeddings_fastembed-0.4.1.dist-info/licenses/LICENSE
llama_index_embeddings_fastembed-0.4.1.dist-info/RECORD
